QrCerUtils/__init__.py
QrCerUtils/decorators/__init__.py
QrCerUtils/decorators/timeout/__init__.py
QrCerUtils/decorators/timeout/decorator_timeout.py
QrCerUtils/loggers/__init__.py
QrCerUtils/loggers/default/__init__.py
QrCerUtils/loggers/default/logger.py
QrCerUtils/utils/__init__.py
QrCerUtils/utils/datetime/__init__.py
QrCerUtils/utils/datetime/util_datetime.py
QrCerUtils/utils/email/__init__.py
QrCerUtils/utils/email/util_email.py
QrCerUtils/utils/encode/__init__.py
QrCerUtils/utils/encode/util_automatic_default_encode.py
QrCerUtils/utils/encode/util_encode.py
QrCerUtils/utils/encode/util_encode_detect.py
QrCerUtils/utils/file/__init__.py
QrCerUtils/utils/file/util_file.py
QrCerUtils/utils/image/__init__.py
QrCerUtils/utils/image/util_image.py
QrCerUtils/utils/redis/__init__.py
QrCerUtils/utils/redis/util_redis.py
QrCerUtils/utils/redis/util_redis_key.py
QrCerUtils/utils/wechat_work/__init__.py
QrCerUtils/utils/wechat_work/util_robot_message_builder.py
QrCerUtils/utils/wechat_work/util_robot_message_sender.py
QrCerUtils-0.1.6.dist-info/LICENSE
QrCerUtils-0.1.6.dist-info/METADATA
QrCerUtils-0.1.6.dist-info/WHEEL
QrCerUtils-0.1.6.dist-info/top_level.txt
QrCerUtils-0.1.6.dist-info/RECORD
